<?xml version="1.0" encoding="UTF-8" standalone="no" ?>
<items>
	<item id="7060" phase="1">
		<info name="Azure Shoulders" name_zh="碧蓝护肩" type="CLOTH" slot="SHOULDERS" unique="no" req_lvl="33" item_lvl="38" quality="UNCOMMON" boe="yes" icon="Inv_shoulder_27.png"/>
		<stats>
			<stat type="ARMOR" value="38"/>
			<stat type="STAMINA" value="5"/>
			<stat type="SPELL_DAMAGE_FROST" value="13"/>
		</stats>
		<source>
			<en>Crafted by Tailorers. Requires Naga Scales.</en>
			<zh>裁缝制造</zh>
		</source>
	</item>

	<item id="4734" phase="1">
		<info name="Mistscape Mantle" name_zh="雾纹衬肩" type="CLOTH" slot="SHOULDERS" unique="no" req_lvl="38" item_lvl="43" quality="UNCOMMON" boe="yes" icon="Inv_shoulder_02.png"/>
		<stats>
			<stat type="ARMOR" value="42"/>
			<stat type="INTELLECT" value="11"/>
			<stat type="SPIRIT" value="5"/>
		</stats>
		<source>
			<en>World drop.</en>
			<zh>世界掉落</zh>
		</source>
	</item>

	<item id="10027" phase="1">
		<info name="Black Mageweave Shoulders" name_zh="黑色魔纹护肩" type="CLOTH" slot="SHOULDERS" unique="no" req_lvl="41" item_lvl="46" quality="UNCOMMON" boe="yes" icon="Inv_shoulder_25.png"/>
		<stats>
			<stat type="ARMOR" value="45"/>
			<stat type="SPIRIT" value="10"/>
			<stat type="INTELLECT" value="9"/>
		</stats>
		<source>
			<en>Crafted by Tailorers. Trivial to craft.</en>
			<zh>裁缝制造</zh>
		</source>
	</item>

	<item id="10028" phase="1">
		<info name="Shadoweave Shoulders" name_zh="暗纹护肩" type="CLOTH" slot="SHOULDERS" unique="no" req_lvl="42" item_lvl="47" quality="UNCOMMON" boe="yes" icon="Inv_shoulder_25.png"/>
		<stats>
			<stat type="ARMOR" value="46"/>
			<stat type="STAMINA" value="7"/>
			<stat type="SPELL_DAMAGE_SHADOW" value="17"/>
		</stats>
		<source>
			<en>Crafted by Tailorers. Trivial to craft.</en>
			<zh>裁缝制造</zh>
		</source>
	</item>

	<item id="10029" phase="1">
		<info name="Red Mageweave Shoulders" name_zh="红色魔纹护肩" type="CLOTH" slot="SHOULDERS" unique="no" req_lvl="42" item_lvl="47" quality="UNCOMMON" boe="yes" icon="Inv_shoulder_23.png"/>
		<stats>
			<stat type="ARMOR" value="46"/>
			<stat type="INTELLECT" value="15"/>
		</stats>
		<source>
			<en>Crafted by Tailorers. Trivial to craft.</en>
			<zh>裁缝制造</zh>
		</source>
	</item>

	<item id="8111" phase="1">
		<info name="Hibernal Mantle" name_zh="寒冬衬肩" type="CLOTH" slot="SHOULDERS" unique="no" req_lvl="43" item_lvl="48" quality="UNCOMMON" boe="yes" icon="Inv_shoulder_18.png"/>
		<stats>
			<stat type="ARMOR" value="47"/>
			<stat type="INTELLECT" value="10"/>
			<stat type="SPIRIT" value="10"/>
		</stats>
		<source>
			<en>World drop.</en>
			<zh>世界掉落</zh>
		</source>
	</item>

	<item id="14443" phase="1">
		<info name="Venomshroud Mantle" name_zh="毒丝衬肩" type="CLOTH" slot="SHOULDERS" unique="no" req_lvl="44" item_lvl="49" quality="UNCOMMON" boe="yes" icon="Inv_shoulder_18.png"/>
		<stats>
			<stat type="ARMOR" value="48"/>
			<stat type="INTELLECT" value="12"/>
			<stat type="STAMINA" value="4"/>
			<stat type="NATURE_RESISTANCE" value="4"/>
		</stats>
		<source>
			<en>World drop.</en>
			<zh>世界掉落</zh>
		</source>
	</item>

	<item id="11310" phase="1">
		<info name="Flameseer Mantle" name_zh="烈焰先知衬肩" type="CLOTH" slot="SHOULDERS" unique="no" req_lvl="42" item_lvl="47" quality="RARE" boe="no" icon="Inv_shoulder_02.png"/>
		<stats>
			<stat type="ARMOR" value="51"/>
			<stat type="SPIRIT" value="10"/>
			<stat type="SPELL_DAMAGE_FIRE" value="14"/>
		</stats>
		<source>
			<en>Drops from Galgann Firehammer in Uldaman.</en>
			<zh>奥达曼加加恩·火锤</zh>
		</source>
	</item>

	<item id="14452" phase="1">
		<info name="Highborne Pauldrons" name_zh="上层精灵肩铠" type="CLOTH" slot="SHOULDERS" unique="no" req_lvl="49" item_lvl="54" quality="UNCOMMON" boe="yes" icon="Inv_shoulder_24.png"/>
		<stats>
			<stat type="ARMOR" value="53"/>
			<stat type="SPIRIT" value="12"/>
			<stat type="STAMINA" value="11"/>
		</stats>
		<source>
			<en>World drop.</en>
			<zh>世界掉落</zh>
		</source>
	</item>

	<item id="11624" phase="1">
		<info name="Kentic Amice" name_zh="肯提克护肩" type="CLOTH" slot="SHOULDERS" unique="no" req_lvl="47" item_lvl="52" quality="RARE" boe="no" icon="Inv_shoulder_25.png"/>
		<stats>
			<stat type="ARMOR" value="56"/>
			<stat type="INTELLECT" value="13"/>
			<stat type="SPIRIT" value="6"/>
			<stat type="STAMINA" value="5"/>
			<stat type="SPELL_DAMAGE" value="14"/>
		</stats>
		<source>
			<en>Drops from High Interrogator Gerstahn in Blackrock Depths.</en>
			<zh>黑石深渊审讯官格斯塔恩</zh>
		</source>
	</item>

	<item id="15812" phase="1">
		<info name="Orchid Amice" name_zh="紫兰花披肩" type="CLOTH" slot="SHOULDERS" unique="no" req_lvl="53" item_lvl="56" quality="UNCOMMON" boe="no" icon="Inv_shoulder_02.png"/>
		<mutex item_id="15813"/>
		<stats>
			<stat type="ARMOR" value="54"/>
			<stat type="INTELLECT" value="15"/>
			<stat type="STAMINA" value="4"/>
			<stat type="STRENGTH" value="4"/>
			<stat type="SPIRIT" value="3"/>
		</stats>
		<source>
			<en>Quest reward. Trivial quest.</en>
			<zh>任务奖励</zh>
		</source>
	</item>

	<item id="13013" phase="1">
		<info name="Elder Wizard's Mantle" name_zh="巫师长者衬肩" type="CLOTH" slot="SHOULDERS" unique="no" req_lvl="51" item_lvl="56" quality="RARE" boe="yes" icon="Inv_shoulder_14.png"/>
		<stats>
			<stat type="ARMOR" value="60"/>
			<stat type="INTELLECT" value="20"/>
			<stat type="SPELL_DAMAGE" value="11"/>
		</stats>
		<source>
			<en>World drop.</en>
			<zh>世界掉落</zh>
		</source>
	</item>

	<item id="11782" phase="1">
		<info name="Boreal Mantle" name_zh="北地衬肩" type="CLOTH" slot="SHOULDERS" unique="no" req_lvl="52" item_lvl="57" quality="RARE" boe="no" icon="Inv_shoulder_02.png"/>
		<stats>
			<stat type="ARMOR" value="61"/>
			<stat type="INTELLECT" value="8"/>
			<stat type="STAMINA" value="5"/>
			<stat type="SPELL_DAMAGE_FROST" value="29"/>
		</stats>
		<source>
			<en>Drops from Warder Stilgiss in Blackrock Depths.</en>
			<zh>黑石深渊典狱官斯迪尔基斯</zh>
		</source>
	</item>

	<item id="12109" phase="1">
		<info name="Azure Moon Amice" name_zh="蓝月披肩" type="CLOTH" slot="SHOULDERS" unique="no" req_lvl="52" item_lvl="58" quality="UNCOMMON" faction="HORDE" boe="no" icon="Inv_shoulder_02.png"/>
		<mutex item_id="12110"/>
		<mutex item_id="12108"/>
		<mutex item_id="12111"/>
		<stats>
			<stat type="ARMOR" value="56"/>
			<stat type="STAMINA" value="8"/>
			<stat type="INTELLECT" value="15"/>
		</stats>
		<source>
			<en>Quest reward. Requires Blackrock Depths.</en>
			<zh>任务奖励</zh>
		</source>
	</item>

	<item id="15784" phase="1">
		<info name="Crystal Breeze Mantle" name_zh="水晶之风衬肩" type="CLOTH" slot="SHOULDERS" unique="no" req_lvl="52" item_lvl="59" quality="UNCOMMON" boe="no" icon="Inv_shoulder_02.png"/>
		<mutex item_id="15786"/>
		<mutex item_id="15787"/>
		<stats>
			<stat type="ARMOR" value="57"/>
			<stat type="SPIRIT" value="13"/>
			<stat type="STAMINA" value="12"/>
		</stats>
		<source>
			<en>Quest reward. Elite quest in Winterspring.</en>
			<zh>任务奖励</zh>
		</source>
	</item>

	<item id="8288" phase="1">
		<info name="Arcane Pads" name_zh="奥术护肩" type="CLOTH" slot="SHOULDERS" unique="no" req_lvl="54" item_lvl="59" quality="UNCOMMON" boe="yes" icon="Inv_shoulder_02.png"/>
		<stats>
			<stat type="ARMOR" value="57"/>
			<stat type="STAMINA" value="4"/>
			<stat type="INTELLECT" value="18"/>
		</stats>
		<source>
			<en>World drop.</en>
			<zh>世界掉落</zh>
		</source>
	</item>

	<item id="13867" phase="1">
		<info name="Runecloth Shoulders" name_zh="符文布护肩" type="CLOTH" slot="SHOULDERS" unique="no" req_lvl="56" item_lvl="61" quality="UNCOMMON" boe="yes" icon="Inv_shoulder_21.png"/>
		<stats>
			<stat type="ARMOR" value="59"/>
			<stat type="INTELLECT" value="15"/>
			<stat type="SPIRIT" value="10"/>
		</stats>
		<source>
			<en>Crafted by Tailorers. Trivial to craft.</en>
			<zh>裁缝制造</zh>
		</source>
	</item>

	<item id="13374" phase="1">
		<info name="Soulstealer Mantle" name_zh="盗灵衬肩" type="CLOTH" slot="SHOULDERS" unique="no" req_lvl="55" item_lvl="60" quality="RARE" boe="no" icon="Inv_shoulder_02.png"/>
		<stats>
			<stat type="ARMOR" value="64"/>
			<stat type="SPIRIT" value="9"/>
			<stat type="INTELLECT" value="22"/>
		</stats>
		<source>
			<en>Drops from Ramstein the Gorger in Stratholme Undead.</en>
			<zh>斯坦索姆吞咽者拉姆斯登</zh>
		</source>
	</item>

	<item id="16689" phase="1">
		<info name="Magister's Mantle" name_zh="博学者衬肩" type="CLOTH" slot="SHOULDERS" unique="no" req_lvl="55" item_lvl="60" quality="RARE" boe="no" icon="Inv_shoulder_23.png"/>
		<stats>
			<stat type="ARMOR" value="64"/>
			<stat type="INTELLECT" value="22"/>
			<stat type="SPIRIT" value="6"/>
			<stat type="STAMINA" value="6"/>
		</stats>
		<source>
			<en>Drops from Ras Frostwhisper in Scholomance.</en>
			<zh>通灵学院莱斯·霜语</zh>
		</source>
	</item>

	<item id="16701" phase="1">
		<info name="Dreadmist Mantle" name_zh="鬼雾衬肩" type="CLOTH" slot="SHOULDERS" unique="no" req_lvl="55" item_lvl="60" quality="RARE" boe="no" icon="Inv_misc_bone_taurenskull_01.png"/>
		<stats>
			<stat type="ARMOR" value="64"/>
			<stat type="INTELLECT" value="15"/>
			<stat type="STAMINA" value="14"/>
			<stat type="SPIRIT" value="9"/>
		</stats>
		<source>
			<en>Drops from Jandice Barov in Scholomance.</en>
			<zh>通灵学院詹迪斯·巴罗夫</zh>
		</source>
	</item>

	<item id="16695" phase="1">
		<info name="Devout Mantle" name_zh="虔诚衬肩" type="CLOTH" slot="SHOULDERS" unique="no" req_lvl="55" item_lvl="60" quality="RARE" boe="no" icon="Inv_shoulder_02.png"/>
		<stats>
			<stat type="ARMOR" value="64"/>
			<stat type="INTELLECT" value="21"/>
			<stat type="SPIRIT" value="9"/>
			<stat type="STAMINA" value="4"/>
		</stats>
		<source>
			<en>Drops from Solakar Flamewreath in Upper Blackrock Spire (UBRS).</en>
			<zh>黑石塔上层索拉卡·火冠</zh>
		</source>
	</item>

	<item id="13185" phase="1">
		<info name="Sunderseer Mantle" name_zh="碎裂先知衬肩" type="CLOTH" slot="SHOULDERS" unique="no" req_lvl="56" item_lvl="61" quality="RARE" boe="no" icon="Inv_shoulder_02.png"/>
		<stats>
			<stat type="ARMOR" value="65"/>
			<stat type="INTELLECT" value="17"/>
			<stat type="SPIRIT" value="11"/>
			<stat type="STAMINA" value="4"/>
			<stat type="SPELL_DAMAGE" value="8"/>
		</stats>
		<source>
			<en>Drops from Crystal Fang in Lower Blackrock Spire (LBRS).</en>
			<zh>黑石塔下层水晶之牙</zh>
		</source>
	</item>

	<item id="14633" phase="1">
		<info name="Necropile Mantle" name_zh="骨堆衬肩" type="CLOTH" slot="SHOULDERS" unique="no" req_lvl="56" item_lvl="61" quality="RARE" boe="no" icon="Inv_shoulder_02.png"/>
		<stats>
			<stat type="ARMOR" value="65"/>
			<stat type="STAMINA" value="17"/>
			<stat type="INTELLECT" value="11"/>
			<stat type="SPIRIT" value="9"/>
		</stats>
		<source>
			<en>Drops from multiple bosses in Scholomance.</en>
			<zh>通灵学院院长室BOSS</zh>
		</source>
	</item>

	<item id="14139" phase="1">
		<info name="Mooncloth Shoulders" name_zh="月布护肩" type="CLOTH" slot="SHOULDERS" unique="no" req_lvl="56" item_lvl="61" quality="RARE" boe="yes" icon="Inv_shoulder_02.png"/>
		<stats>
			<stat type="ARMOR" value="65"/>
			<stat type="INTELLECT" value="17"/>
			<stat type="SPIRIT" value="11"/>
			<stat type="STAMINA" value="9"/>
		</stats>
		<source>
			<en>Crafted by Tailorers. Requires Mooncloth.</en>
			<zh>裁缝制造</zh>
		</source>
	</item>

	<item id="14112" phase="1">
		<info name="Felcloth Shoulders" name_zh="恶魔布护肩" type="CLOTH" slot="SHOULDERS" unique="no" req_lvl="57" item_lvl="62" quality="UNCOMMON" boe="yes" icon="Inv_shoulder_23.png"/>
		<stats>
			<stat type="ARMOR" value="60"/>
			<stat type="SPIRIT" value="5"/>
			<stat type="SPELL_DAMAGE_SHADOW" value="26"/>
		</stats>
		<source>
			<en>Crafted by Tailorers. Requires Felcloth and Demonic Runes.</en>
			<zh>裁缝制造</zh>
		</source>
	</item>

	<item id="14538" phase="1">
		<info name="Deadwalker Mantle" name_zh="行尸衬肩" type="CLOTH" slot="SHOULDERS" unique="no" req_lvl="57" item_lvl="62" quality="RARE" boe="no" icon="Inv_shoulder_02.png"/>
		<stats>
			<stat type="ARMOR" value="66"/>
			<stat type="STAMINA" value="19"/>
			<stat type="INTELLECT" value="9"/>
			<stat type="SPELL_DAMAGE_SHADOW" value="13"/>
		</stats>
		<source>
			<en>Drops from Rattlegore in Scholomance.</en>
			<zh>通灵学院血骨傀儡</zh>
		</source>
	</item>

	<item id="16797" phase="1">
		<info name="Arcanist Mantle" name_zh="奥术师衬肩" type="CLOTH" slot="SHOULDERS" unique="no" req_lvl="60" item_lvl="66" quality="EPIC" boe="no" icon="Inv_shoulder_02.png"/>
		<class_restriction class="MAGE"/>
		<stats>
			<stat type="ARMOR" value="76"/>
			<stat type="INTELLECT" value="21"/>
			<stat type="SPIRIT" value="5"/>
			<stat type="STAMINA" value="10"/>
			<stat type="SHADOW_RESISTANCE" value="7"/>
			<stat type="MANA_PER_5" value="4"/>
			<stat type="SPELL_DAMAGE" value="14"/>
		</stats>
		<source>
			<en>Drops from Baron Geddon in Molten Core.</en>
			<zh>熔火之心迦顿男爵</zh>
		</source>
	</item>

	<item id="18681" phase="1">
		<info name="Burial Shawl" name_zh="葬礼披肩" type="CLOTH" slot="SHOULDERS" unique="no" req_lvl="56" item_lvl="61" quality="RARE" boe="no" icon="Inv_shoulder_05.png"/>
		<stats>
			<stat type="ARMOR" value="65"/>
			<stat type="INTELLECT" value="16"/>
			<stat type="SPELL_DAMAGE" value="20"/>
		</stats>
		<source>
			<en>Drops from multiple bosses in Scholomance.</en>
			<zh>通灵学院院长室BOSS</zh>
		</source>
	</item>

	<item id="18757" phase="2">
		<info name="Diabolic Mantle" name_zh="恶魔衬肩" type="CLOTH" slot="SHOULDERS" unique="no" req_lvl="57" item_lvl="62" quality="RARE" boe="no" icon="Inv_shoulder_25.png"/>
		<stats>
			<stat type="ARMOR" value="66"/>
			<stat type="STAMINA" value="16"/>
			<stat type="MANA_PER_5" value="8"/>
		</stats>
		<source>
			<en>Drops from Lord Hel'nurath in Dire Maul.</en>
			<zh>厄运之槌西赫尔努拉斯</zh>
		</source>
	</item>

	<item id="18720" phase="2">
		<info name="Shroud of the Nathrezim" name_zh="纳斯雷兹姆护肩" type="CLOTH" slot="SHOULDERS" unique="no" req_lvl="60" item_lvl="63" quality="RARE" boe="no" icon="Inv_shoulder_23.png"/>
		<stats>
			<stat type="ARMOR" value="67"/>
			<stat type="INTELLECT" value="16"/>
			<stat type="SPIRIT" value="10"/>
			<stat type="SPELL_CRIT_CHANCE" value="0.01"/>
		</stats>
		<source>
			<en>Drops from Balnazzar in Stratholme Living.</en>
			<zh>斯坦索姆巴纳扎尔</zh>
		</source>
	</item>

	<item id="23319" phase="2">
		<info name="Lieutenant Commander's Silk Mantle" name_zh="少校的丝质衬肩" type="CLOTH" slot="SHOULDERS" unique="no" req_lvl="60" item_lvl="71" quality="RARE" faction="ALLIANCE" boe="no" icon="Inv_shoulder_02.png"/>
		<class_restriction class="MAGE"/>
		<stats>
			<stat type="ARMOR" value="135"/>
			<stat type="STAMINA" value="14"/>
			<stat type="INTELLECT" value="11"/>
			<stat type="SPIRIT" value="4"/>
			<stat type="SPELL_DAMAGE" value="15"/>
			<stat type="SPELL_CRIT_CHANCE" value="0.01"/>
		</stats>
		<source>
			<en>May be purchased upon reaching Lieutenant Commander (rank 10). Alliance only.</en>
			<zh>联盟荣誉奖励，需要少校军阶</zh>
		</source>
	</item>

	<item id="23264" phase="2">
		<info name="Champion's Silk Mantle" name_zh="勇士的丝质衬肩" type="CLOTH" slot="SHOULDERS" unique="no" req_lvl="60" item_lvl="71" quality="RARE" faction="HORDE" boe="no" icon="Inv_shoulder_02.png"/>
		<class_restriction class="MAGE"/>
		<stats>
			<stat type="ARMOR" value="135"/>
			<stat type="STAMINA" value="14"/>
			<stat type="INTELLECT" value="11"/>
			<stat type="SPIRIT" value="4"/>
			<stat type="SPELL_DAMAGE" value="15"/>
			<stat type="SPELL_CRIT_CHANCE" value="0.01"/>
		</stats>
		<source>
			<en>May be purchased upon reaching Champion (rank 10). Horde only.</en>
			<zh>部落荣誉奖励，需要勇士军阶</zh>
		</source>
	</item>

	<item id="16444" phase="2">
		<info name="Field Marshal's Silk Spaulders" name_zh="元帅的丝质肩甲" type="CLOTH" slot="SHOULDERS" unique="no" req_lvl="60" item_lvl="74" quality="EPIC" faction="ALLIANCE" boe="no" icon="Inv_shoulder_23.png"/>
		<class_restriction class="MAGE"/>
		<stats>
			<stat type="ARMOR" value="135"/>
			<stat type="STAMINA" value="21"/>
			<stat type="INTELLECT" value="15"/>
			<stat type="SPIRIT" value="5"/>
			<stat type="SPELL_DAMAGE" value="25"/>
			<stat type="SPELL_PENETRATION" value="10"/>
		</stats>
		<source>
			<en>May be purchased upon reaching Field Marshal (rank 13). Alliance only.</en>
			<zh>联盟荣誉奖励，需要元帅军阶</zh>
		</source>
	</item>

	<item id="16536" phase="2">
		<info name="Warlord's Silk Amice" name_zh="督军的丝质披肩" type="CLOTH" slot="SHOULDERS" unique="no" req_lvl="60" item_lvl="74" quality="EPIC" faction="HORDE" boe="no" icon="Inv_shoulder_19.png"/>
		<class_restriction class="MAGE"/>
		<stats>
			<stat type="ARMOR" value="135"/>
			<stat type="STAMINA" value="21"/>
			<stat type="INTELLECT" value="15"/>
			<stat type="SPIRIT" value="5"/>
			<stat type="SPELL_DAMAGE" value="25"/>
			<stat type="SPELL_PENETRATION" value="10"/>
		</stats>
		<source>
			<en>May be purchased upon reaching Warlord (rank 13). Horde only.</en>
			<zh>部落荣誉奖励，需要督军军阶</zh>
		</source>
	</item>

	<item id="19507" phase="3">
		<info name="Inquisitor's Shawl" name_zh="审讯者披肩" type="CLOTH" slot="SHOULDERS" unique="no" req_lvl="36" item_lvl="41" quality="UNCOMMON" boe="no" icon="Inv_shoulder_27.png"/>
		<stats>
			<stat type="ARMOR" value="40"/>
			<stat type="INTELLECT" value="8"/>
			<stat type="SPELL_DAMAGE" value="9"/>
		</stats>
		<source>
			<en>Drops from High Inquisitor Fairbanks in Scarlet Monastery (SM).</en>
			<zh>血色修道院大检察官法尔班克斯</zh>
		</source>
	</item>

	<item id="19050" phase="3">
		<info name="Mantle of the Timbermaw" name_zh="木喉衬肩" type="CLOTH" slot="SHOULDERS" unique="no" req_lvl="59" item_lvl="64" quality="RARE" boe="yes" icon="Inv_shoulder_19.png"/>
		<stats>
			<stat type="ARMOR" value="68"/>
			<stat type="INTELLECT" value="21"/>
			<stat type="MANA_PER_5" value="6"/>
		</stats>
		<source>
			<en>Crafted by Tailorers. Requires Mooncloth and Essences (Living and Earth).</en>
			<zh>裁缝制造</zh>
		</source>
	</item>

	<item id="19059" phase="3">
		<info name="Argent Shoulders" name_zh="银色护肩" type="CLOTH" slot="SHOULDERS" unique="no" req_lvl="59" item_lvl="64" quality="RARE" boe="yes" icon="Inv_shoulder_13.png"/>
		<stats>
			<stat type="ARMOR" value="68"/>
			<stat type="STAMINA" value="23"/>
			<stat type="SPIRIT" value="8"/>
			<stat type="SHADOW_RESISTANCE" value="5"/>
		</stats>
		<source>
			<en>Crafted by Tailorers. Requires Mooncloth and Guardian Stones.</en>
			<zh>裁缝制造</zh>
		</source>
	</item>

	<item id="19370" phase="3">
		<info name="Mantle of the Blackwing Cabal" name_zh="黑翼衬肩" type="CLOTH" slot="SHOULDERS" unique="no" req_lvl="60" item_lvl="73" quality="EPIC" boe="no" icon="Inv_shoulder_25.png"/>
		<stats>
			<stat type="ARMOR" value="84"/>
			<stat type="INTELLECT" value="16"/>
			<stat type="STAMINA" value="12"/>
			<stat type="SPELL_DAMAGE" value="34"/>
		</stats>
		<source>
			<en>Drops from Razorgore the Untamed in Blackwing Lair.</en>
			<zh>黑翼之巢狂野的拉佐格尔</zh>
		</source>
	</item>

	<item id="16917" phase="3">
		<info name="Netherwind Mantle" name_zh="灵风衬肩" type="CLOTH" slot="SHOULDERS" unique="no" req_lvl="60" item_lvl="76" quality="EPIC" boe="no" icon="Inv_shoulder_32.png"/>
		<class_restriction class="MAGE"/>
		<stats>
			<stat type="ARMOR" value="87"/>
			<stat type="INTELLECT" value="13"/>
			<stat type="SPIRIT" value="12"/>
			<stat type="STAMINA" value="16"/>
			<stat type="FIRE_RESISTANCE" value="10"/>
			<stat type="MANA_PER_5" value="4"/>
			<stat type="SPELL_DAMAGE" value="21"/>
		</stats>
		<source>
			<en>Drops from Nefarian in Blackwing Lair.</en>
			<zh>黑翼之巢克洛玛古斯</zh>
		</source>
	</item>

	<item id="16932" phase="3">
		<info name="Nemesis Spaulders" name_zh="复仇肩铠" type="CLOTH" slot="SHOULDERS" unique="no" req_lvl="60" item_lvl="76" quality="EPIC" boe="no" icon="Inv_shoulder_19.png"/>
		<class_restriction class="WARLOCK"/>
		<stats>
			<stat type="ARMOR" value="87"/>
			<stat type="INTELLECT" value="13"/>
			<stat type="SPIRIT" value="6"/>
			<stat type="STAMINA" value="20"/>
			<stat type="FIRE_RESISTANCE" value="10"/>
			<stat type="HEALTH_PER_5" value="4"/>
			<stat type="SPELL_DAMAGE" value="23"/>
		</stats>
		<source>
			<en>Drops from Nefarian in Blackwing Lair.</en>
			<zh>黑翼之巢克洛玛古斯</zh>
		</source>
	</item>

	<item id="19845" phase="4">
		<info name="Zandalar Illusionist's Mantle" name_zh="赞达拉幻术师衬肩" type="CLOTH" slot="SHOULDERS" unique="no" req_lvl="60" item_lvl="61" quality="EPIC" boe="no" icon="Inv_shoulder_17.png"/>
		<class_restriction class="MAGE"/>
		<stats>
			<stat type="ARMOR" value="71"/>
			<stat type="INTELLECT" value="21"/>
			<stat type="STAMINA" value="13"/>
			<stat type="SPIRIT" value="10"/>
			<stat type="SPELL_DAMAGE" value="12"/>
		</stats>
		<source>
			<en>Quest reward. Requires boss drops from Zul'Gurub and Honored with Zandalar Tribe.</en>
			<zh>任务奖励</zh>
		</source>
	</item>

	<item id="20061" phase="4">
		<info name="Highlander's Epaulets" name_zh="高地肩饰" type="CLOTH" slot="SHOULDERS" unique="no" req_lvl="60" item_lvl="65" quality="EPIC" faction="ALLIANCE" boe="no" icon="Inv_shoulder_24.png"/>
		<class_restriction class="MAGE"/>
		<class_restriction class="PRIEST"/>
		<class_restriction class="WARLOCK"/>
		<stats>
			<stat type="ARMOR" value="185"/>
			<stat type="STAMINA" value="18"/>
			<stat type="INTELLECT" value="17"/>
			<stat type="SPELL_DAMAGE" value="12"/>
			<stat type="MANA_PER_5" value="4"/>
		</stats>
		<source>
			<en>Requires Exalted with The League of Arathor (Arathi Basin).</en>
			<zh>阿拉索联军崇拜</zh>
		</source>
	</item>

	<item id="20176" phase="4">
		<info name="Defiler's Epaulets" name_zh="污染者肩饰" type="CLOTH" slot="SHOULDERS" unique="no" req_lvl="60" item_lvl="65" quality="EPIC" faction="HORDE" boe="no" icon="Inv_shoulder_24.png"/>
		<class_restriction class="MAGE"/>
		<class_restriction class="PRIEST"/>
		<class_restriction class="WARLOCK"/>
		<stats>
			<stat type="ARMOR" value="185"/>
			<stat type="STAMINA" value="18"/>
			<stat type="INTELLECT" value="17"/>
			<stat type="SPELL_DAMAGE" value="12"/>
			<stat type="MANA_PER_5" value="4"/>
		</stats>
		<source>
			<en>Requires Exalted with The Defilers (Arathi Basin).</en>
			<zh>污染者崇拜</zh>
		</source>
	</item>

	<item id="22305" phase="5">
		<info name="Ironweave Mantle" name_zh="铁纹衬肩" type="CLOTH" slot="SHOULDERS" unique="no" req_lvl="56" item_lvl="61" quality="RARE" boe="no" icon="Inv_shoulder_05.png"/>
		<class_restriction class="MAGE"/>
		<class_restriction class="PRIEST"/>
		<class_restriction class="WARLOCK"/>
		<stats>
			<stat type="ARMOR" value="155"/>
			<stat type="STAMINA" value="17"/>
			<stat type="INTELLECT" value="11"/>
		</stats>
		<source>
			<en>Drops from multiple bosses in Scholomance.</en>
			<zh>通灵学院院长室BOSS</zh>
		</source>
	</item>

	<item id="22412" phase="5">
		<info name="Thuzadin Mantle" name_zh="图萨丁衬肩" type="CLOTH" slot="SHOULDERS" unique="no" req_lvl="58" item_lvl="63" quality="RARE" boe="no" icon="Inv_shoulder_02.png"/>
		<stats>
			<stat type="ARMOR" value="67"/>
			<stat type="STAMINA" value="11"/>
			<stat type="INTELLECT" value="18"/>
			<stat type="SPELL_DAMAGE" value="12"/>
		</stats>
		<source>
			<en>Drops from Baron Rivendare in Stratholme Undead.</en>
			<zh>斯坦索姆瑞文戴尔男爵</zh>
		</source>
	</item>

	<item id="22068" phase="5">
		<info name="Sorcerer's Mantle" name_zh="巫师衬肩" type="CLOTH" slot="SHOULDERS" unique="no" req_lvl="60" item_lvl="65" quality="RARE" boe="no" icon="Inv_shoulder_23.png"/>
		<class_restriction class="MAGE"/>
		<stats>
			<stat type="ARMOR" value="69"/>
			<stat type="INTELLECT" value="17"/>
			<stat type="SPIRIT" value="7"/>
			<stat type="STAMINA" value="11"/>
			<stat type="SPELL_DAMAGE" value="9"/>
		</stats>
		<source>
			<en>Quest reward. Requires Magister's Boots, Magister's Leggings, Magister's Mantle.</en>
			<zh>任务奖励</zh>
		</source>
	</item>

	<item id="20686" phase="4">
		<info name="Abyssal Cloth Amice of Sorcery" name_zh="深渊布质肩饰" type="CLOTH" slot="SHOULDERS" unique="no" req_lvl="60" item_lvl="68" quality="RARE" boe="no" icon="Inv_shoulder_25.png"/>
		<stats>
			<stat type="ARMOR" value="72"/>
			<stat type="STAMINA" value="13"/>
			<stat type="INTELLECT" value="13"/>
			<stat type="SPELL_DAMAGE" value="15"/>
			<stat type="SPELL_HIT_CHANCE" value="0.01"/>
		</stats>
		<source>
			<en>Drops from Baron Kazum, a summonable raid boss in Silithus.</en>
			<zh>希利苏斯风石卡苏姆男爵</zh>
		</source>
	</item>

	<item id="21468" phase="5">
		<info name="Mantle of Maz'Nadir" name_zh="玛兹纳迪尔衬肩" type="CLOTH" slot="SHOULDERS" unique="no" req_lvl="60" item_lvl="74" quality="RARE" boe="no" icon="Inv_shoulder_25.png"/>
		<stats>
			<stat type="ARMOR" value="78"/>
			<stat type="STAMINA" value="11"/>
			<stat type="INTELLECT" value="15"/>
			<stat type="SPIRIT" value="7"/>
			<stat type="SPELL_DAMAGE" value="21"/>
		</stats>
		<source>
			<en>Drops from Moam in Ruins of Ahn'Qiraj (AQ20).</en>
			<zh>安其拉废墟莫阿姆</zh>
		</source>
	</item>

	<item id="21686" phase="5">
		<info name="Mantle of Phrenic Power" name_zh="精神力量衬肩" type="CLOTH" slot="SHOULDERS" unique="no" req_lvl="60" item_lvl="76" quality="EPIC" boe="no" icon="Inv_shoulder_02.png"/>
		<stats>
			<stat type="ARMOR" value="87"/>
			<stat type="INTELLECT" value="20"/>
			<stat type="STAMINA" value="20"/>
			<stat type="SPELL_DAMAGE_FIRE" value="33"/>
		</stats>
		<source>
			<en>Drops from Princess Yauj in Temple of Ahn'Qiraj (AQ40).</en>
			<zh>安其拉亚尔基公主</zh>
		</source>
	</item>

	<item id="21345" phase="5">
		<info name="Enigma Shoulderpads" name_zh="神秘肩垫" type="CLOTH" slot="SHOULDERS" unique="no" req_lvl="60" item_lvl="78" quality="EPIC" boe="no" icon="Inv_shoulder_03.png"/>
		<class_restriction class="MAGE"/>
		<stats>
			<stat type="ARMOR" value="89"/>
			<stat type="INTELLECT" value="12"/>
			<stat type="SPIRIT" value="4"/>
			<stat type="STAMINA" value="16"/>
			<stat type="SPELL_DAMAGE" value="30"/>
			<stat type="SPELL_PENETRATION" value="10"/>
			<stat type="MANA_PER_5" value="4"/>
		</stats>
		<source>
			<en>Quest reward. Requires boss drops from Temple of Ahn'Qiraj (AQ40).</en>
			<zh>任务奖励</zh>
		</source>
	</item>

	<item id="22758" phase="6">
		<info name="Sylvan Shoulders" name_zh="林栖者护肩" type="CLOTH" slot="SHOULDERS" unique="no" req_lvl="60" item_lvl="70" quality="RARE" boe="yes" icon="Inv_shoulder_18.png"/>
		<stats>
			<stat type="ARMOR" value="74"/>
			<stat type="STAMINA" value="18"/>
			<stat type="NATURE_RESISTANCE" value="20"/>
			<stat type="SPELL_DAMAGE" value="7"/>
		</stats>
		<source>
			<en>Crafted by Tailorers. Requires Living Essences.</en>
			<zh>裁缝制造</zh>
		</source>
	</item>

	<item id="22983" phase="6">
		<info name="Rime Covered Mantle" name_zh="蒙霜衬肩" type="CLOTH" slot="SHOULDERS" unique="no" req_lvl="60" item_lvl="83" quality="EPIC" boe="no" icon="Inv_shoulder_05.png"/>
		<stats>
			<stat type="ARMOR" value="94"/>
			<stat type="INTELLECT" value="12"/>
			<stat type="STAMINA" value="12"/>
			<stat type="SPELL_DAMAGE" value="39"/>
			<stat type="SPELL_CRIT_CHANCE" value="0.01"/>
		</stats>
		<source>
			<en>Drops from Gluth in Naxxramas.</en>
			<zh>纳克萨玛斯格拉斯</zh>
		</source>
	</item>

	<item id="22968" phase="6">
		<info name="Glacial Mantle" name_zh="冰川衬肩" type="CLOTH" slot="SHOULDERS" unique="no" req_lvl="60" item_lvl="83" quality="EPIC" boe="no" icon="Inv_shoulder_14.png"/>
		<stats>
			<stat type="ARMOR" value="94"/>
			<stat type="STAMINA" value="18"/>
			<stat type="FROST_RESISTANCE" value="33"/>
			<stat type="SPELL_DAMAGE" value="16"/>
		</stats>
		<source>
			<en>Drops from Grobbulus in Naxxramas.</en>
			<zh>纳克萨玛斯格罗布鲁斯</zh>
		</source>
	</item>

	<item id="22499" phase="6">
		<info name="Frostfire Shoulderpads" name_zh="霜火肩垫" type="CLOTH" slot="SHOULDERS" unique="no" req_lvl="60" item_lvl="86" quality="EPIC" boe="no" icon="Inv_shoulder_25.png"/>
		<class_restriction class="MAGE"/>
		<stats>
			<stat type="ARMOR" value="97"/>
			<stat type="STAMINA" value="17"/>
			<stat type="INTELLECT" value="18"/>
			<stat type="SPIRIT" value="9"/>
			<stat type="SPELL_DAMAGE" value="36"/>
		</stats>
		<source>
			<en>Quest reward. Requires boss drops from Naxxramas.</en>
			<zh>NAXX套装</zh>
		</source>
	</item>
</items>
