<?xml version="1.0" encoding="UTF-8" standalone="no" ?>
<items>
	<item id="18714" phase="1">
		<info name="Ancient Sinew Wrapped Lamina" name_zh="龙筋箭袋" type="QUIVER" slot="QUIVER" unique="yes" req_lvl="60" item_lvl="75" quality="EPIC" boe="no" icon="Inv_misc_quiver_03.png"/>
		<class_restriction class="HUNTER"/>
		<stats>
			<stat type="RANGED_ATTACK_SPEED" value="15"/>
		</stats>
		<source>
			<en>Quest reward.</en>
			<zh>任务奖励</zh>
		</source>
	</item>
	
	<item id="19319" phase="1">
		<info name="Harpy Hide Quiver" name_zh="鹰身人皮箭袋" type="QUIVER" slot="QUIVER" unique="yes" req_lvl="55" item_lvl="60" quality="RARE" boe="no" icon="Inv_misc_quiver_06.png"/>
		<stats>
			<stat type="RANGED_ATTACK_SPEED" value="15"/>
		</stats>
		<source>
			<en>AV vendors.</en>
			<zh>奥山声望崇敬/zh>
		</source>
	</item>

	<item id="19320" phase="1">
		<info name="Gnoll Skin Bandolier" name_zh="豺狼人皮弹药包" type="AMMO_POUCH" slot="QUIVER" unique="yes" req_lvl="55" item_lvl="60" quality="RARE" boe="no" icon="Inv_misc_ammo_bullet_01.png"/>
		<stats>
			<stat type="RANGED_ATTACK_SPEED" value="15"/>
		</stats>
		<source>
			<en>AV vendors.</en>
			<zh>奥山声望崇敬</zh>
		</source>
	</item>
	
	<item id="2662" phase="1">
		<info name="Ribbly's Quiver" name_zh="雷布里的箭袋" type="QUIVER" slot="QUIVER" unique="yes" req_lvl="50" item_lvl="55" quality="UNCOMMON" boe="no" icon="Inv_misc_quiver_06.png"/>
		<stats>
			<stat type="RANGED_ATTACK_SPEED" value="14"/>
		</stats>
		<source>
			<en>Drops from Ribbly Screwspigot in Blackrock Depths.</en>
			<zh>黑石深渊雷布里·斯库比格特</zh>
		</source>
	</item>
	
	<item id="2663" phase="1">
		<info name="Ribbly's Bandolier" name_zh="雷布里的油布包" type="AMMO_POUCH" slot="QUIVER" unique="yes" req_lvl="50" item_lvl="55" quality="UNCOMMON" boe="no" icon="Inv_misc_ammo_bullet_01.png"/>
		<stats>
			<stat type="RANGED_ATTACK_SPEED" value="14"/>
		</stats>
		<source>
			<en>Drops from Ribbly Screwspigot in Blackrock Depths.</en>
			<zh>黑石深渊雷布里·斯库比格特</zh>
		</source>
	</item>
	
	<item id="8217" phase="1">
		<info name="Quickdraw Quiver" name_zh="快捷箭袋" type="QUIVER" slot="QUIVER" unique="no" req_lvl="40" item_lvl="45" quality="UNCOMMON" boe="yes" icon="Inv_misc_quiver_07.png"/>
		<stats>
			<stat type="RANGED_ATTACK_SPEED" value="13"/>
		</stats>
		<source>
			<en>Crafted by leatherworkers.</en>
			<zh>制皮制造</zh>
		</source>
	</item>
	
	<item id="8218" phase="1">
		<info name="Thick Leather Ammo Pouch" name_zh="厚皮弹药包" type="AMMO_POUCH" slot="QUIVER" unique="no" req_lvl="40" item_lvl="45" quality="UNCOMMON" boe="yes" icon="Inv_misc_bag_09_black.png"/>
		<stats>
			<stat type="RANGED_ATTACK_SPEED" value="13"/>
		</stats>
		<source>
			<en>Crafted by leatherworkers.</en>
			<zh>制皮制造</zh>
		</source>
	</item>
</items>
